{
  "$schema": "https://json-schema.org/draft/2020-12/schema",
  "title": "CmdOverrides",
  "type": "object",
  "properties": {
    "additional_params": {
      "title": "Additional Parameters",
      "description": "Additional parameters to append to the base command",
      "type": [
        "array",
        "null"
      ],
      "items": {
        "type": "string"
      }
    },
    "base_command_override": {
      "title": "Base Command Override",
      "description": "Override the base command with a custom command",
      "type": [
        "string",
        "null"
      ]
    }
  }
}